completeness/__init__.py
completeness/completeness.py
completeness_ratio_check-0.1.dist-info/METADATA
completeness_ratio_check-0.1.dist-info/WHEEL
completeness_ratio_check-0.1.dist-info/top_level.txt
completeness_ratio_check-0.1.dist-info/RECORD
